bilateral_egyptian/__init__.py
bilateral_egyptian/analysis.py
bilateral_egyptian/compounds.py
bilateral_egyptian/mirror_pairs.py
bilateral_egyptian/pbwah.py
bilateral_egyptian/stratification.py
bilateral_egyptian-0.2.0.dist-info/licenses/LICENSE
bilateral_egyptian-0.2.0.dist-info/METADATA
bilateral_egyptian-0.2.0.dist-info/WHEEL
bilateral_egyptian-0.2.0.dist-info/top_level.txt
bilateral_egyptian-0.2.0.dist-info/RECORD
