Metadata-Version: 2.4
Name: bilateral-egyptian
Version: 0.2.0
Summary: Tools for analyzing bilateral semantic structure in Egyptian hieroglyphics with PBWAH acceleration
Author-email: Nicholas David Brown <research@bilateral-egyptian.org>
License-Expression: MIT
Project-URL: Homepage, https://github.com/bilateral-egyptian/bilateral-egyptian
Project-URL: Bug Tracker, https://github.com/bilateral-egyptian/bilateral-egyptian/issues
Project-URL: Documentation, https://bilateral-egyptian.readthedocs.io
Project-URL: Paper: Bilateral Covenant, https://doi.org/10.5281/zenodo.18168786
Project-URL: Paper: Dictionary, https://doi.org/10.5281/zenodo.18169109
Project-URL: Paper: PBWAH Algorithm, https://doi.org/10.5281/zenodo.18168195
Keywords: egyptology,hieroglyphics,linguistics,bilateral,phonemic,semantic,ancient-egypt,anagram,hashing
Classifier: Development Status :: 3 - Alpha
Classifier: Intended Audience :: Science/Research
Classifier: Operating System :: OS Independent
Classifier: Programming Language :: Python :: 3
Classifier: Programming Language :: Python :: 3.8
Classifier: Programming Language :: Python :: 3.9
Classifier: Programming Language :: Python :: 3.10
Classifier: Programming Language :: Python :: 3.11
Classifier: Programming Language :: Python :: 3.12
Classifier: Topic :: Scientific/Engineering
Classifier: Topic :: Text Processing :: Linguistic
Requires-Python: >=3.8
License-File: LICENSE
Dynamic: license-file
